{
 "as_of": "2026-06-17 21:11 UTC",
 "baskets": {
  "bigdata": {
   "label": "AI & Big Data",
   "source": "CoinMarketCap \u00b7 AI & Big Data category, top 20 by market cap",
   "coins": [
    {
     "rank": 1,
     "id": 6535,
     "symbol": "NEAR",
     "name": "NEAR Protocol",
     "slug": "near-protocol",
     "price": 2.263066137716457,
     "change_1h": 1.07,
     "change_24h": -4.11,
     "change_7d": 15.28,
     "market_cap": 2938582424.87,
     "volume_24h": 385695819.1666976
    },
    {
     "rank": 2,
     "id": 22974,
     "symbol": "TAO",
     "name": "Bittensor",
     "slug": "bittensor",
     "price": 246.13743029075135,
     "change_1h": -0.66,
     "change_24h": -3.79,
     "change_7d": 23.19,
     "market_cap": 2714211869.68,
     "volume_24h": 325594590.72056514
    },
    {
     "rank": 3,
     "id": 8916,
     "symbol": "ICP",
     "name": "Internet Computer",
     "slug": "internet-computer",
     "price": 2.3611688071906896,
     "change_1h": 0.14,
     "change_24h": -0.59,
     "change_7d": 6.51,
     "market_cap": 1308421527.38,
     "volume_24h": 77806455.3295886
    },
    {
     "rank": 4,
     "id": 5690,
     "symbol": "RENDER",
     "name": "Render",
     "slug": "render",
     "price": 1.6820636552483061,
     "change_1h": 0.48,
     "change_24h": -3.91,
     "change_7d": 11.64,
     "market_cap": 872607696.92,
     "volume_24h": 40582001.23125978
    },
    {
     "rank": 5,
     "id": 35509,
     "symbol": "VVV",
     "name": "Venice Token",
     "slug": "venice-token",
     "price": 15.969996191280051,
     "change_1h": 0.05,
     "change_24h": 2.63,
     "change_7d": 21.03,
     "market_cap": 746782663.06,
     "volume_24h": 57290387.24443136
    },
    {
     "rank": 6,
     "id": 2280,
     "symbol": "FIL",
     "name": "Filecoin",
     "slug": "filecoin",
     "price": 0.7935099018904432,
     "change_1h": 0.75,
     "change_24h": -1.99,
     "change_7d": 9.28,
     "market_cap": 627166183.9,
     "volume_24h": 102766691.72030339
    },
    {
     "rank": 7,
     "id": 3987,
     "symbol": "BDX",
     "name": "Beldex",
     "slug": "beldex",
     "price": 0.07956739503244319,
     "change_1h": -0.07,
     "change_24h": -0.34,
     "change_7d": 0.38,
     "market_cap": 615719424.89,
     "volume_24h": 8212310.91955195
    },
    {
     "rank": 8,
     "id": 7226,
     "symbol": "INJ",
     "name": "Injective",
     "slug": "injective",
     "price": 5.460301999078211,
     "change_1h": 0.88,
     "change_24h": -3.92,
     "change_7d": 9.79,
     "market_cap": 545871602.71,
     "volume_24h": 129992828.01052815
    },
    {
     "rank": 9,
     "id": 3773,
     "symbol": "FET",
     "name": "Artificial Superintelligence Alliance",
     "slug": "artificial-superintelligence-alliance",
     "price": 0.20228400198689986,
     "change_1h": 0.05,
     "change_24h": -3.23,
     "change_7d": 8.57,
     "market_cap": 456935507.69,
     "volume_24h": 133692846.6319401
    },
    {
     "rank": 10,
     "id": 29420,
     "symbol": "VIRTUAL",
     "name": "Virtuals Protocol",
     "slug": "virtual-protocol",
     "price": 0.6061840360348215,
     "change_1h": -0.08,
     "change_24h": -4.15,
     "change_7d": 11.86,
     "market_cap": 398297810.22,
     "volume_24h": 70389183.00210874
    },
    {
     "rank": 11,
     "id": 38828,
     "symbol": "KITE",
     "name": "Kite",
     "slug": "kite",
     "price": 0.18474017783655264,
     "change_1h": 0.6,
     "change_24h": -2.33,
     "change_7d": 7.41,
     "market_cap": 332532320.11,
     "volume_24h": 28873178.64330912
    },
    {
     "rank": 12,
     "id": 36300,
     "symbol": "SKYAI",
     "name": "SKYAI",
     "slug": "skyai",
     "price": 0.3301466065056408,
     "change_1h": -3.27,
     "change_24h": -26.05,
     "change_7d": 83.08,
     "market_cap": 330146606.51,
     "volume_24h": 52484497.19060422
    },
    {
     "rank": 13,
     "id": 38339,
     "symbol": "UB",
     "name": "Unibase",
     "slug": "unibase",
     "price": 0.11840450913139786,
     "change_1h": -0.21,
     "change_24h": -4.48,
     "change_7d": -14.42,
     "market_cap": 296011272.83,
     "volume_24h": 9784732.63817222
    },
    {
     "rank": 14,
     "id": 7431,
     "symbol": "AKT",
     "name": "Akash Network",
     "slug": "akash-network",
     "price": 0.7456359734077003,
     "change_1h": -3.37,
     "change_24h": -7.36,
     "change_7d": 30.19,
     "market_cap": 219874025.47,
     "volume_24h": 18117178.6196595
    },
    {
     "rank": 15,
     "id": 6719,
     "symbol": "GRT",
     "name": "The Graph",
     "slug": "the-graph",
     "price": 0.019468613501308154,
     "change_1h": 0.23,
     "change_24h": -2.19,
     "change_7d": 4.67,
     "market_cap": 211309516.09,
     "volume_24h": 16225473.70699872
    },
    {
     "rank": 16,
     "id": 2467,
     "symbol": "TRAC",
     "name": "OriginTrail",
     "slug": "origintrail",
     "price": 0.3485227453791229,
     "change_1h": -0.72,
     "change_24h": -4.45,
     "change_7d": 2.2,
     "market_cap": 174261372.69,
     "volume_24h": 3430253.90162578
    },
    {
     "rank": 17,
     "id": 2416,
     "symbol": "THETA",
     "name": "Theta Network",
     "slug": "theta-network",
     "price": 0.16186735444810096,
     "change_1h": 0.6,
     "change_24h": -0.83,
     "change_7d": 9.62,
     "market_cap": 161867354.45,
     "volume_24h": 8817653.61060268
    },
    {
     "rank": 18,
     "id": 38984,
     "symbol": "GUA",
     "name": "SUPERFORTUNE",
     "slug": "superfortune",
     "price": 1.1051189289055101,
     "change_1h": 0.32,
     "change_24h": 21.99,
     "change_7d": 102.53,
     "market_cap": 138139866.11,
     "volume_24h": 2247310.35077992
    },
    {
     "rank": 19,
     "id": 1697,
     "symbol": "BAT",
     "name": "Basic Attention Token",
     "slug": "basic-attention-token",
     "price": 0.09178224526395258,
     "change_1h": 1.53,
     "change_24h": 0.47,
     "change_7d": 0.5,
     "market_cap": 137280967.31,
     "volume_24h": 10554469.39687012
    },
    {
     "rank": 20,
     "id": 34958,
     "symbol": "TAG",
     "name": "Tagger",
     "slug": "tagger",
     "price": 0.0012654032532524817,
     "change_1h": -0.06,
     "change_24h": 22.55,
     "change_7d": 28.83,
     "market_cap": 137175498.83,
     "volume_24h": 8715717.39177654
    }
   ]
  },
  "agents": {
   "label": "AI Agents",
   "source": "CoinMarketCap \u00b7 AI Agents category, top 20 by market cap",
   "coins": [
    {
     "rank": 1,
     "id": 3773,
     "symbol": "FET",
     "name": "Artificial Superintelligence Alliance",
     "slug": "artificial-superintelligence-alliance",
     "price": 0.20228400198689986,
     "change_1h": 0.05,
     "change_24h": -3.23,
     "change_7d": 8.57,
     "market_cap": 456935507.69,
     "volume_24h": 133692846.6319401
    },
    {
     "rank": 2,
     "id": 29420,
     "symbol": "VIRTUAL",
     "name": "Virtuals Protocol",
     "slug": "virtual-protocol",
     "price": 0.6061840360348215,
     "change_1h": -0.08,
     "change_24h": -4.15,
     "change_7d": 11.86,
     "market_cap": 398297810.22,
     "volume_24h": 70389183.00210874
    },
    {
     "rank": 3,
     "id": 38828,
     "symbol": "KITE",
     "name": "Kite",
     "slug": "kite",
     "price": 0.18474017783655264,
     "change_1h": 0.6,
     "change_24h": -2.33,
     "change_7d": 7.41,
     "market_cap": 332532320.11,
     "volume_24h": 28873178.64330912
    },
    {
     "rank": 4,
     "id": 38339,
     "symbol": "UB",
     "name": "Unibase",
     "slug": "unibase",
     "price": 0.11840450913139786,
     "change_1h": -0.21,
     "change_24h": -4.48,
     "change_7d": -14.42,
     "market_cap": 296011272.83,
     "volume_24h": 9784732.63817222
    },
    {
     "rank": 5,
     "id": 2467,
     "symbol": "TRAC",
     "name": "OriginTrail",
     "slug": "origintrail",
     "price": 0.3485227453791229,
     "change_1h": -0.72,
     "change_24h": -4.45,
     "change_7d": 2.2,
     "market_cap": 174261372.69,
     "volume_24h": 3430253.90162578
    },
    {
     "rank": 6,
     "id": 34926,
     "symbol": "ARC",
     "name": "AI Rig Complex",
     "slug": "ai-rig-complex",
     "price": 0.08389265434436236,
     "change_1h": 0.3,
     "change_24h": 13.5,
     "change_7d": 1.3,
     "market_cap": 83892513.32,
     "volume_24h": 6374121.63583505
    },
    {
     "rank": 7,
     "id": 38908,
     "symbol": "ALLO",
     "name": "Allora",
     "slug": "allora",
     "price": 0.36551316683317464,
     "change_1h": 2.18,
     "change_24h": -1.28,
     "change_7d": -5.6,
     "market_cap": 73285389.95,
     "volume_24h": 47458512.03901476
    },
    {
     "rank": 8,
     "id": 18031,
     "symbol": "CCD",
     "name": "Concordium",
     "slug": "concordium",
     "price": 0.00447841483125276,
     "change_1h": -0.09,
     "change_24h": -2.14,
     "change_7d": -4.93,
     "market_cap": 56482288.69,
     "volume_24h": 125628.9329761
    },
    {
     "rank": 9,
     "id": 35766,
     "symbol": "SIREN",
     "name": "siren",
     "slug": "siren-bsc",
     "price": 0.0743832103346577,
     "change_1h": 44.14,
     "change_24h": 50.87,
     "change_7d": -89.81,
     "market_cap": 53889833.93,
     "volume_24h": 26107839.11720689
    },
    {
     "rank": 10,
     "id": 37545,
     "symbol": "BNKR",
     "name": "BankrCoin",
     "slug": "bankr-coin",
     "price": 0.00046175504562072177,
     "change_1h": 0.16,
     "change_24h": -3.14,
     "change_7d": 2.47,
     "market_cap": 45852276.03,
     "volume_24h": 6391944.03837739
    },
    {
     "rank": 11,
     "id": 33964,
     "symbol": "SERV",
     "name": "OpenServ",
     "slug": "openserv",
     "price": 0.05661315142603214,
     "change_1h": -1.81,
     "change_24h": -10.01,
     "change_7d": -12.18,
     "market_cap": 43592126.6,
     "volume_24h": 1023647.57451102
    },
    {
     "rank": 12,
     "id": 1637,
     "symbol": "RLC",
     "name": "iExec RLC",
     "slug": "rlc",
     "price": 0.3449961565238779,
     "change_1h": 0.41,
     "change_24h": -1.94,
     "change_7d": 4.86,
     "market_cap": 30014591.44,
     "volume_24h": 2039363.12912648
    },
    {
     "rank": 13,
     "id": 34083,
     "symbol": "ZEREBRO",
     "name": "Zerebro",
     "slug": "zerebro",
     "price": 0.02908071734759051,
     "change_1h": 3.66,
     "change_24h": 26.28,
     "change_7d": 17.88,
     "market_cap": 29079215.55,
     "volume_24h": 12709719.79247094
    },
    {
     "rank": 14,
     "id": 37562,
     "symbol": "AIO",
     "name": "OLAXBT",
     "slug": "olaxbt",
     "price": 0.10981307130954003,
     "change_1h": 1.55,
     "change_24h": -1.96,
     "change_7d": -15.95,
     "market_cap": 25284459.67,
     "volume_24h": 2056957.87567898
    },
    {
     "rank": 15,
     "id": 34103,
     "symbol": "AIXBT",
     "name": "aixbt",
     "slug": "aixbt",
     "price": 0.022987432396475698,
     "change_1h": 0.43,
     "change_24h": -0.24,
     "change_7d": 12.19,
     "market_cap": 22962487.98,
     "volume_24h": 7924179.10710534
    },
    {
     "rank": 16,
     "id": 2930,
     "symbol": "IQ",
     "name": "IQ",
     "slug": "iq",
     "price": 0.0008282173117567329,
     "change_1h": 0.03,
     "change_24h": -0.54,
     "change_7d": 6.04,
     "market_cap": 21808584.69,
     "volume_24h": 561281.58106628
    },
    {
     "rank": 17,
     "id": 30963,
     "symbol": "ZENT",
     "name": "Zentry",
     "slug": "zentry",
     "price": 0.0025182285177932535,
     "change_1h": -0.06,
     "change_24h": -1.01,
     "change_7d": -2.45,
     "market_cap": 20170033.48,
     "volume_24h": 1670712.79954685
    },
    {
     "rank": 18,
     "id": 23756,
     "symbol": "CGPT",
     "name": "ChainGPT",
     "slug": "chaingpt",
     "price": 0.02079904838491113,
     "change_1h": 0.4,
     "change_24h": -2.2,
     "change_7d": 2.92,
     "market_cap": 19402037.34,
     "volume_24h": 8315542.94016639
    },
    {
     "rank": 19,
     "id": 38717,
     "symbol": "BLUAI",
     "name": "Bluwhale",
     "slug": "bluwhale",
     "price": 0.015471135121610934,
     "change_1h": 7.35,
     "change_24h": 10.33,
     "change_7d": 28.64,
     "market_cap": 18998553.93,
     "volume_24h": 14498874.2971214
    },
    {
     "rank": 20,
     "id": 34285,
     "symbol": "CLANKER",
     "name": "tokenbot",
     "slug": "tokenbot-2",
     "price": 15.647230456821216,
     "change_1h": -0.27,
     "change_24h": -7.46,
     "change_7d": 14.84,
     "market_cap": 15432507.53,
     "volume_24h": 3058967.37369724
    }
   ]
  }
 }
}