{
 "as_of": "2026-06-20 13:15 UTC",
 "baskets": {
  "bigdata": {
   "label": "AI & Big Data",
   "source": "CoinMarketCap \u00b7 AI & Big Data category, top 20 by market cap",
   "coins": [
    {
     "rank": 1,
     "id": 6535,
     "symbol": "NEAR",
     "name": "NEAR Protocol",
     "slug": "near-protocol",
     "price": 2.1510412896279143,
     "change_1h": 0.55,
     "change_24h": 0.97,
     "change_7d": 4.55,
     "market_cap": 2793576122.94,
     "volume_24h": 197178161.58571863
    },
    {
     "rank": 2,
     "id": 22974,
     "symbol": "TAO",
     "name": "Bittensor",
     "slug": "bittensor",
     "price": 231.5740219563439,
     "change_1h": 0.27,
     "change_24h": 1.88,
     "change_7d": -6.9,
     "market_cap": 2555837189.17,
     "volume_24h": 317888155.9261699
    },
    {
     "rank": 3,
     "id": 7326,
     "symbol": "DEXE",
     "name": "DeXe",
     "slug": "dexe",
     "price": 15.318110147322269,
     "change_1h": -0.69,
     "change_24h": -7.1,
     "change_7d": -13.5,
     "market_cap": 1282641757.64,
     "volume_24h": 13818887.27807111
    },
    {
     "rank": 4,
     "id": 8916,
     "symbol": "ICP",
     "name": "Internet Computer",
     "slug": "internet-computer",
     "price": 2.2824492144254847,
     "change_1h": -0.38,
     "change_24h": 2.12,
     "change_7d": -7.66,
     "market_cap": 1264813022.7,
     "volume_24h": 35082178.77708282
    },
    {
     "rank": 5,
     "id": 5690,
     "symbol": "RENDER",
     "name": "Render",
     "slug": "render",
     "price": 1.7310444711708761,
     "change_1h": -0.75,
     "change_24h": 1.85,
     "change_7d": -2.68,
     "market_cap": 898017577.72,
     "volume_24h": 29423778.88723352
    },
    {
     "rank": 6,
     "id": 35509,
     "symbol": "VVV",
     "name": "Venice Token",
     "slug": "venice-token",
     "price": 14.572304132671,
     "change_1h": -0.31,
     "change_24h": 1.91,
     "change_7d": -14.2,
     "market_cap": 683026503.19,
     "volume_24h": 21672880.78375677
    },
    {
     "rank": 7,
     "id": 3987,
     "symbol": "BDX",
     "name": "Beldex",
     "slug": "beldex",
     "price": 0.08108154525633204,
     "change_1h": 0.83,
     "change_24h": -2.72,
     "change_7d": 1.89,
     "market_cap": 627437648.63,
     "volume_24h": 10090376.86599981
    },
    {
     "rank": 8,
     "id": 2280,
     "symbol": "FIL",
     "name": "Filecoin",
     "slug": "filecoin",
     "price": 0.7839685712536157,
     "change_1h": -0.01,
     "change_24h": 1.19,
     "change_7d": -0.39,
     "market_cap": 619870439.94,
     "volume_24h": 50601584.65383738
    },
    {
     "rank": 9,
     "id": 7226,
     "symbol": "INJ",
     "name": "Injective",
     "slug": "injective",
     "price": 5.077002759121853,
     "change_1h": -0.18,
     "change_24h": 0.05,
     "change_7d": -3.6,
     "market_cap": 507552811.83,
     "volume_24h": 62217144.65353157
    },
    {
     "rank": 10,
     "id": 3773,
     "symbol": "FET",
     "name": "Artificial Superintelligence Alliance",
     "slug": "artificial-superintelligence-alliance",
     "price": 0.1898123166072175,
     "change_1h": 0.27,
     "change_24h": -2.12,
     "change_7d": -8.1,
     "market_cap": 428763453.38,
     "volume_24h": 140317594.83753747
    },
    {
     "rank": 11,
     "id": 29420,
     "symbol": "VIRTUAL",
     "name": "Virtuals Protocol",
     "slug": "virtual-protocol",
     "price": 0.6050239512017779,
     "change_1h": -0.54,
     "change_24h": 0.3,
     "change_7d": -5.53,
     "market_cap": 397543290.08,
     "volume_24h": 45825627.19908436
    },
    {
     "rank": 12,
     "id": 36300,
     "symbol": "SKYAI",
     "name": "SKYAI",
     "slug": "skyai",
     "price": 0.3552293372473867,
     "change_1h": 2.66,
     "change_24h": -0.39,
     "change_7d": 3.16,
     "market_cap": 355229337.25,
     "volume_24h": 26733562.2617189
    },
    {
     "rank": 13,
     "id": 38828,
     "symbol": "KITE",
     "name": "Kite",
     "slug": "kite",
     "price": 0.16562645257060385,
     "change_1h": 1.0,
     "change_24h": -8.03,
     "change_7d": -15.4,
     "market_cap": 298127614.63,
     "volume_24h": 36729424.44115339
    },
    {
     "rank": 14,
     "id": 7431,
     "symbol": "AKT",
     "name": "Akash Network",
     "slug": "akash-network",
     "price": 0.7765362391244016,
     "change_1h": 0.64,
     "change_24h": 4.63,
     "change_7d": 19.28,
     "market_cap": 229054565.55,
     "volume_24h": 8996192.59471908
    },
    {
     "rank": 15,
     "id": 6719,
     "symbol": "GRT",
     "name": "The Graph",
     "slug": "the-graph",
     "price": 0.01956053882781227,
     "change_1h": -0.42,
     "change_24h": 0.02,
     "change_7d": -1.84,
     "market_cap": 212610050.41,
     "volume_24h": 13145144.56591571
    },
    {
     "rank": 16,
     "id": 38339,
     "symbol": "UB",
     "name": "Unibase",
     "slug": "unibase",
     "price": 0.07640726451461827,
     "change_1h": 1.1,
     "change_24h": -36.62,
     "change_7d": -42.29,
     "market_cap": 191018161.29,
     "volume_24h": 24833874.73555667
    },
    {
     "rank": 17,
     "id": 2416,
     "symbol": "THETA",
     "name": "Theta Network",
     "slug": "theta-network",
     "price": 0.15307494598429508,
     "change_1h": -0.03,
     "change_24h": -0.5,
     "change_7d": -4.61,
     "market_cap": 153074945.98,
     "volume_24h": 6441852.1749625
    },
    {
     "rank": 18,
     "id": 1697,
     "symbol": "BAT",
     "name": "Basic Attention Token",
     "slug": "basic-attention-token",
     "price": 0.08811609162089176,
     "change_1h": -0.85,
     "change_24h": -0.43,
     "change_7d": -1.17,
     "market_cap": 131797410.91,
     "volume_24h": 7884439.73096961
    },
    {
     "rank": 19,
     "id": 35763,
     "symbol": "KAITO",
     "name": "KAITO",
     "slug": "kaito",
     "price": 0.47743538562959353,
     "change_1h": 0.02,
     "change_24h": -5.87,
     "change_7d": 8.73,
     "market_cap": 115247597.31,
     "volume_24h": 13987993.63495264
    },
    {
     "rank": 20,
     "id": 38868,
     "symbol": "SENT",
     "name": "Sentient",
     "slug": "sentient",
     "price": 0.015378266997674276,
     "change_1h": -0.46,
     "change_24h": -7.4,
     "change_7d": -7.53,
     "market_cap": 111306034.02,
     "volume_24h": 14682718.27162545
    }
   ]
  },
  "agents": {
   "label": "AI Agents",
   "source": "CoinMarketCap \u00b7 AI Agents category, top 20 by market cap",
   "coins": [
    {
     "rank": 1,
     "id": 3773,
     "symbol": "FET",
     "name": "Artificial Superintelligence Alliance",
     "slug": "artificial-superintelligence-alliance",
     "price": 0.1898123166072175,
     "change_1h": 0.27,
     "change_24h": -2.12,
     "change_7d": -8.1,
     "market_cap": 428763453.38,
     "volume_24h": 140317594.83753747
    },
    {
     "rank": 2,
     "id": 29420,
     "symbol": "VIRTUAL",
     "name": "Virtuals Protocol",
     "slug": "virtual-protocol",
     "price": 0.6050239512017779,
     "change_1h": -0.54,
     "change_24h": 0.3,
     "change_7d": -5.53,
     "market_cap": 397543290.08,
     "volume_24h": 45825627.19908436
    },
    {
     "rank": 3,
     "id": 38828,
     "symbol": "KITE",
     "name": "Kite",
     "slug": "kite",
     "price": 0.16562645257060385,
     "change_1h": 1.0,
     "change_24h": -8.03,
     "change_7d": -15.4,
     "market_cap": 298127614.63,
     "volume_24h": 36729424.44115339
    },
    {
     "rank": 4,
     "id": 38339,
     "symbol": "UB",
     "name": "Unibase",
     "slug": "unibase",
     "price": 0.07640726451461827,
     "change_1h": 1.1,
     "change_24h": -36.62,
     "change_7d": -42.29,
     "market_cap": 191018161.29,
     "volume_24h": 24833874.73555667
    },
    {
     "rank": 5,
     "id": 2467,
     "symbol": "TRAC",
     "name": "OriginTrail",
     "slug": "origintrail",
     "price": 0.34227260554470995,
     "change_1h": 0.4,
     "change_24h": 0.84,
     "change_7d": -6.01,
     "market_cap": 171136302.77,
     "volume_24h": 2786244.03120045
    },
    {
     "rank": 6,
     "id": 38908,
     "symbol": "ALLO",
     "name": "Allora",
     "slug": "allora",
     "price": 0.39991499080595944,
     "change_1h": 1.09,
     "change_24h": 4.61,
     "change_7d": 2.96,
     "market_cap": 80182955.66,
     "volume_24h": 44962540.81480488
    },
    {
     "rank": 7,
     "id": 34926,
     "symbol": "ARC",
     "name": "AI Rig Complex",
     "slug": "ai-rig-complex",
     "price": 0.079566879495128,
     "change_1h": 0.75,
     "change_24h": -2.28,
     "change_7d": -10.15,
     "market_cap": 79566745.74,
     "volume_24h": 3261808.57330454
    },
    {
     "rank": 8,
     "id": 18031,
     "symbol": "CCD",
     "name": "Concordium",
     "slug": "concordium",
     "price": 0.004294847208033488,
     "change_1h": -0.31,
     "change_24h": 0.67,
     "change_7d": -0.05,
     "market_cap": 54182040.37,
     "volume_24h": 112849.06300665
    },
    {
     "rank": 9,
     "id": 35766,
     "symbol": "SIREN",
     "name": "siren",
     "slug": "siren-bsc",
     "price": 0.06882638063076638,
     "change_1h": 76.37,
     "change_24h": -2.98,
     "change_7d": -45.61,
     "market_cap": 49860213.16,
     "volume_24h": 20366193.72770026
    },
    {
     "rank": 10,
     "id": 34083,
     "symbol": "ZEREBRO",
     "name": "Zerebro",
     "slug": "zerebro",
     "price": 0.044581233094012664,
     "change_1h": -1.59,
     "change_24h": -7.28,
     "change_7d": 65.39,
     "market_cap": 44578930.75,
     "volume_24h": 26836824.37607296
    },
    {
     "rank": 11,
     "id": 37545,
     "symbol": "BNKR",
     "name": "BankrCoin",
     "slug": "bankr-coin",
     "price": 0.0004358514768750708,
     "change_1h": -0.1,
     "change_24h": 0.55,
     "change_7d": -12.67,
     "market_cap": 43280051.65,
     "volume_24h": 4036669.26424026
    },
    {
     "rank": 12,
     "id": 33964,
     "symbol": "SERV",
     "name": "OpenServ",
     "slug": "openserv",
     "price": 0.049885752109380434,
     "change_1h": -0.62,
     "change_24h": 1.3,
     "change_7d": -16.71,
     "market_cap": 38412029.12,
     "volume_24h": 697488.43959194
    },
    {
     "rank": 13,
     "id": 6841,
     "symbol": "PHA",
     "name": "Phala Network",
     "slug": "phala-network",
     "price": 0.03698236471611102,
     "change_1h": -0.39,
     "change_24h": -0.92,
     "change_7d": 2.68,
     "market_cap": 31075801.45,
     "volume_24h": 14108266.02914265
    },
    {
     "rank": 14,
     "id": 37562,
     "symbol": "AIO",
     "name": "OLAXBT",
     "slug": "olaxbt",
     "price": 0.12611558266816048,
     "change_1h": -0.08,
     "change_24h": 3.77,
     "change_7d": -5.6,
     "market_cap": 29038112.91,
     "volume_24h": 2396520.52575118
    },
    {
     "rank": 15,
     "id": 1637,
     "symbol": "RLC",
     "name": "iExec RLC",
     "slug": "rlc",
     "price": 0.32776894648738597,
     "change_1h": -0.09,
     "change_24h": 0.64,
     "change_7d": -6.96,
     "market_cap": 28515827.87,
     "volume_24h": 1208488.85365598
    },
    {
     "rank": 16,
     "id": 34103,
     "symbol": "AIXBT",
     "name": "aixbt",
     "slug": "aixbt",
     "price": 0.0225307388396498,
     "change_1h": -0.54,
     "change_24h": 3.79,
     "change_7d": -5.77,
     "market_cap": 22506290.0,
     "volume_24h": 10602908.31794804
    },
    {
     "rank": 17,
     "id": 2930,
     "symbol": "IQ",
     "name": "IQ",
     "slug": "iq",
     "price": 0.0008253836421944878,
     "change_1h": 1.36,
     "change_24h": 3.15,
     "change_7d": 2.88,
     "market_cap": 21733968.62,
     "volume_24h": 987759.03385341
    },
    {
     "rank": 18,
     "id": 30963,
     "symbol": "ZENT",
     "name": "Zentry",
     "slug": "zentry",
     "price": 0.002518438393988475,
     "change_1h": 0.09,
     "change_24h": 1.15,
     "change_7d": -3.16,
     "market_cap": 20171714.51,
     "volume_24h": 1211307.34982192
    },
    {
     "rank": 19,
     "id": 34285,
     "symbol": "CLANKER",
     "name": "tokenbot",
     "slug": "tokenbot-2",
     "price": 18.819219375068233,
     "change_1h": 3.16,
     "change_24h": 14.52,
     "change_7d": 32.12,
     "market_cap": 18560968.06,
     "volume_24h": 4800573.815679
    },
    {
     "rank": 20,
     "id": 23756,
     "symbol": "CGPT",
     "name": "ChainGPT",
     "slug": "chaingpt",
     "price": 0.019773953050234754,
     "change_1h": -0.81,
     "change_24h": -1.15,
     "change_7d": -5.92,
     "market_cap": 18445879.93,
     "volume_24h": 7933349.81585529
    }
   ]
  }
 }
}