{
 "as_of": "2026-06-17 22:32 UTC",
 "baskets": {
  "bigdata": {
   "label": "AI & Big Data",
   "source": "CoinMarketCap \u00b7 AI & Big Data category, top 20 by market cap",
   "coins": [
    {
     "rank": 1,
     "id": 6535,
     "symbol": "NEAR",
     "name": "NEAR Protocol",
     "slug": "near-protocol",
     "price": 2.2350472291366956,
     "change_1h": -0.69,
     "change_24h": -4.02,
     "change_7d": 13.69,
     "market_cap": 2902199884.61,
     "volume_24h": 388368147.0923566
    },
    {
     "rank": 2,
     "id": 22974,
     "symbol": "TAO",
     "name": "Bittensor",
     "slug": "bittensor",
     "price": 246.49145726874025,
     "change_1h": 0.99,
     "change_24h": -3.49,
     "change_7d": 23.95,
     "market_cap": 2718131701.65,
     "volume_24h": 330522063.1695684
    },
    {
     "rank": 3,
     "id": 8916,
     "symbol": "ICP",
     "name": "Internet Computer",
     "slug": "internet-computer",
     "price": 2.3406723398503066,
     "change_1h": -0.4,
     "change_24h": -1.56,
     "change_7d": 7.01,
     "market_cap": 1297063585.06,
     "volume_24h": 79340841.48439398
    },
    {
     "rank": 4,
     "id": 7326,
     "symbol": "DEXE",
     "name": "DeXe",
     "slug": "dexe",
     "price": 14.801024872140374,
     "change_1h": -0.1,
     "change_24h": -20.73,
     "change_7d": -16.42,
     "market_cap": 1239344303.85,
     "volume_24h": 36145328.37758313
    },
    {
     "rank": 5,
     "id": 5690,
     "symbol": "RENDER",
     "name": "Render",
     "slug": "render",
     "price": 1.6923991076524914,
     "change_1h": 0.68,
     "change_24h": -2.84,
     "change_7d": 13.17,
     "market_cap": 877969441.29,
     "volume_24h": 42303786.20818849
    },
    {
     "rank": 6,
     "id": 35509,
     "symbol": "VVV",
     "name": "Venice Token",
     "slug": "venice-token",
     "price": 15.7531883967234,
     "change_1h": -0.73,
     "change_24h": 1.14,
     "change_7d": 19.79,
     "market_cap": 736651208.84,
     "volume_24h": 56815758.06733211
    },
    {
     "rank": 7,
     "id": 2280,
     "symbol": "FIL",
     "name": "Filecoin",
     "slug": "filecoin",
     "price": 0.7945101562608207,
     "change_1h": 0.42,
     "change_24h": -1.91,
     "change_7d": 9.65,
     "market_cap": 627961076.78,
     "volume_24h": 103937201.98905864
    },
    {
     "rank": 8,
     "id": 3987,
     "symbol": "BDX",
     "name": "Beldex",
     "slug": "beldex",
     "price": 0.07995347510185055,
     "change_1h": 0.46,
     "change_24h": 0.26,
     "change_7d": 1.28,
     "market_cap": 618707103.04,
     "volume_24h": 8101402.26813278
    },
    {
     "rank": 9,
     "id": 7226,
     "symbol": "INJ",
     "name": "Injective",
     "slug": "injective",
     "price": 5.430342381476266,
     "change_1h": -1.0,
     "change_24h": -3.04,
     "change_7d": 10.5,
     "market_cap": 542876511.14,
     "volume_24h": 130673886.10972789
    },
    {
     "rank": 10,
     "id": 3773,
     "symbol": "FET",
     "name": "Artificial Superintelligence Alliance",
     "slug": "artificial-superintelligence-alliance",
     "price": 0.19996520462867748,
     "change_1h": -0.91,
     "change_24h": -3.67,
     "change_7d": 8.21,
     "market_cap": 451697620.18,
     "volume_24h": 138203103.2092428
    },
    {
     "rank": 11,
     "id": 29420,
     "symbol": "VIRTUAL",
     "name": "Virtuals Protocol",
     "slug": "virtual-protocol",
     "price": 0.6015670232435427,
     "change_1h": -0.38,
     "change_24h": -4.35,
     "change_7d": 12.08,
     "market_cap": 395264167.02,
     "volume_24h": 71877420.3714329
    },
    {
     "rank": 12,
     "id": 36300,
     "symbol": "SKYAI",
     "name": "SKYAI",
     "slug": "skyai",
     "price": 0.3377760235328829,
     "change_1h": -0.08,
     "change_24h": -24.22,
     "change_7d": 100.68,
     "market_cap": 337776023.53,
     "volume_24h": 52771420.1172629
    },
    {
     "rank": 13,
     "id": 38828,
     "symbol": "KITE",
     "name": "Kite",
     "slug": "kite",
     "price": 0.18537031441323212,
     "change_1h": 0.16,
     "change_24h": -2.3,
     "change_7d": 6.17,
     "market_cap": 333666565.94,
     "volume_24h": 28945212.9798973
    },
    {
     "rank": 14,
     "id": 38339,
     "symbol": "UB",
     "name": "Unibase",
     "slug": "unibase",
     "price": 0.11799361453261249,
     "change_1h": -0.07,
     "change_24h": -1.97,
     "change_7d": -15.44,
     "market_cap": 294984036.33,
     "volume_24h": 9291928.22597005
    },
    {
     "rank": 15,
     "id": 7431,
     "symbol": "AKT",
     "name": "Akash Network",
     "slug": "akash-network",
     "price": 0.7540880669466689,
     "change_1h": 1.41,
     "change_24h": -6.46,
     "change_7d": 32.96,
     "market_cap": 222367940.73,
     "volume_24h": 18611629.98251513
    },
    {
     "rank": 16,
     "id": 6719,
     "symbol": "GRT",
     "name": "The Graph",
     "slug": "the-graph",
     "price": 0.01949085271234832,
     "change_1h": 0.05,
     "change_24h": -2.36,
     "change_7d": 5.31,
     "market_cap": 211550897.17,
     "volume_24h": 16440331.56494192
    },
    {
     "rank": 17,
     "id": 2467,
     "symbol": "TRAC",
     "name": "OriginTrail",
     "slug": "origintrail",
     "price": 0.34760788233980655,
     "change_1h": -0.76,
     "change_24h": -4.31,
     "change_7d": 1.55,
     "market_cap": 173803941.17,
     "volume_24h": 3546571.40219631
    },
    {
     "rank": 18,
     "id": 2416,
     "symbol": "THETA",
     "name": "Theta Network",
     "slug": "theta-network",
     "price": 0.161075572492018,
     "change_1h": -0.2,
     "change_24h": -0.97,
     "change_7d": 9.33,
     "market_cap": 161075572.49,
     "volume_24h": 8940506.05270282
    },
    {
     "rank": 19,
     "id": 37298,
     "symbol": "VELVET",
     "name": "Velvet",
     "slug": "velvet",
     "price": 0.334409136200707,
     "change_1h": -1.07,
     "change_24h": -23.65,
     "change_7d": -56.5,
     "market_cap": 140716406.88,
     "volume_24h": 16486948.92972074
    },
    {
     "rank": 20,
     "id": 38984,
     "symbol": "GUA",
     "name": "SUPERFORTUNE",
     "slug": "superfortune",
     "price": 1.104460076270911,
     "change_1h": 1.88,
     "change_24h": 26.9,
     "change_7d": 92.91,
     "market_cap": 138057509.53,
     "volume_24h": 2238952.87545925
    }
   ]
  },
  "agents": {
   "label": "AI Agents",
   "source": "CoinMarketCap \u00b7 AI Agents category, top 20 by market cap",
   "coins": [
    {
     "rank": 1,
     "id": 3773,
     "symbol": "FET",
     "name": "Artificial Superintelligence Alliance",
     "slug": "artificial-superintelligence-alliance",
     "price": 0.19996520462867748,
     "change_1h": -0.91,
     "change_24h": -3.67,
     "change_7d": 8.21,
     "market_cap": 451697620.18,
     "volume_24h": 138203103.2092428
    },
    {
     "rank": 2,
     "id": 29420,
     "symbol": "VIRTUAL",
     "name": "Virtuals Protocol",
     "slug": "virtual-protocol",
     "price": 0.6015670232435427,
     "change_1h": -0.38,
     "change_24h": -4.35,
     "change_7d": 12.08,
     "market_cap": 395264167.02,
     "volume_24h": 71877420.3714329
    },
    {
     "rank": 3,
     "id": 38828,
     "symbol": "KITE",
     "name": "Kite",
     "slug": "kite",
     "price": 0.18537031441323212,
     "change_1h": 0.16,
     "change_24h": -2.3,
     "change_7d": 6.17,
     "market_cap": 333666565.94,
     "volume_24h": 28945212.9798973
    },
    {
     "rank": 4,
     "id": 38339,
     "symbol": "UB",
     "name": "Unibase",
     "slug": "unibase",
     "price": 0.11799361453261249,
     "change_1h": -0.07,
     "change_24h": -1.97,
     "change_7d": -15.44,
     "market_cap": 294984036.33,
     "volume_24h": 9291928.22597005
    },
    {
     "rank": 5,
     "id": 2467,
     "symbol": "TRAC",
     "name": "OriginTrail",
     "slug": "origintrail",
     "price": 0.34760788233980655,
     "change_1h": -0.76,
     "change_24h": -4.31,
     "change_7d": 1.55,
     "market_cap": 173803941.17,
     "volume_24h": 3546571.40219631
    },
    {
     "rank": 6,
     "id": 34926,
     "symbol": "ARC",
     "name": "AI Rig Complex",
     "slug": "ai-rig-complex",
     "price": 0.08430197594816065,
     "change_1h": -0.01,
     "change_24h": 14.44,
     "change_7d": 1.35,
     "market_cap": 84301834.24,
     "volume_24h": 6368670.23393635
    },
    {
     "rank": 7,
     "id": 38908,
     "symbol": "ALLO",
     "name": "Allora",
     "slug": "allora",
     "price": 0.3688892649968491,
     "change_1h": -1.32,
     "change_24h": -0.91,
     "change_7d": -4.19,
     "market_cap": 73962297.63,
     "volume_24h": 49819173.85857543
    },
    {
     "rank": 8,
     "id": 18031,
     "symbol": "CCD",
     "name": "Concordium",
     "slug": "concordium",
     "price": 0.0044771438319886,
     "change_1h": -0.12,
     "change_24h": -2.25,
     "change_7d": -5.02,
     "market_cap": 56466258.7,
     "volume_24h": 124852.96536053
    },
    {
     "rank": 9,
     "id": 35766,
     "symbol": "SIREN",
     "name": "siren",
     "slug": "siren-bsc",
     "price": 0.07439209041144959,
     "change_1h": 44.92,
     "change_24h": 53.61,
     "change_7d": -90.21,
     "market_cap": 53896267.45,
     "volume_24h": 25725174.24698455
    },
    {
     "rank": 10,
     "id": 37545,
     "symbol": "BNKR",
     "name": "BankrCoin",
     "slug": "bankr-coin",
     "price": 0.00045428142102782974,
     "change_1h": -1.41,
     "change_24h": -5.02,
     "change_7d": 0.68,
     "market_cap": 45110145.11,
     "volume_24h": 6423165.05529156
    },
    {
     "rank": 11,
     "id": 33964,
     "symbol": "SERV",
     "name": "OpenServ",
     "slug": "openserv",
     "price": 0.05645061746310764,
     "change_1h": -0.56,
     "change_24h": -10.14,
     "change_7d": -10.71,
     "market_cap": 43466975.45,
     "volume_24h": 1061556.34050691
    },
    {
     "rank": 12,
     "id": 6841,
     "symbol": "PHA",
     "name": "Phala Network",
     "slug": "phala-network",
     "price": 0.0355570948438662,
     "change_1h": -0.6,
     "change_24h": -0.02,
     "change_7d": 18.58,
     "market_cap": 29873716.03,
     "volume_24h": 16623122.14201413
    },
    {
     "rank": 13,
     "id": 1637,
     "symbol": "RLC",
     "name": "iExec RLC",
     "slug": "rlc",
     "price": 0.3417794035373699,
     "change_1h": -0.74,
     "change_24h": -2.33,
     "change_7d": 4.73,
     "market_cap": 29734734.62,
     "volume_24h": 2175310.22491246
    },
    {
     "rank": 14,
     "id": 34083,
     "symbol": "ZEREBRO",
     "name": "Zerebro",
     "slug": "zerebro",
     "price": 0.029551273671491952,
     "change_1h": 1.54,
     "change_24h": 28.29,
     "change_7d": 17.75,
     "market_cap": 29549747.58,
     "volume_24h": 13155952.3539057
    },
    {
     "rank": 15,
     "id": 37562,
     "symbol": "AIO",
     "name": "OLAXBT",
     "slug": "olaxbt",
     "price": 0.11179992859373691,
     "change_1h": 0.64,
     "change_24h": -0.4,
     "change_7d": -18.27,
     "market_cap": 25741933.56,
     "volume_24h": 2110614.14233785
    },
    {
     "rank": 16,
     "id": 34103,
     "symbol": "AIXBT",
     "name": "aixbt",
     "slug": "aixbt",
     "price": 0.022767817121375857,
     "change_1h": -0.66,
     "change_24h": -0.96,
     "change_7d": 12.23,
     "market_cap": 22743111.02,
     "volume_24h": 8053371.05514339
    },
    {
     "rank": 17,
     "id": 2930,
     "symbol": "IQ",
     "name": "IQ",
     "slug": "iq",
     "price": 0.0008245298167466895,
     "change_1h": -0.28,
     "change_24h": -0.23,
     "change_7d": 6.67,
     "market_cap": 21711485.72,
     "volume_24h": 538237.65558668
    },
    {
     "rank": 18,
     "id": 30963,
     "symbol": "ZENT",
     "name": "Zentry",
     "slug": "zentry",
     "price": 0.0025193932492803455,
     "change_1h": 0.1,
     "change_24h": -0.86,
     "change_7d": -2.52,
     "market_cap": 20179362.53,
     "volume_24h": 1674350.59827838
    },
    {
     "rank": 19,
     "id": 23756,
     "symbol": "CGPT",
     "name": "ChainGPT",
     "slug": "chaingpt",
     "price": 0.020936426163858123,
     "change_1h": 0.74,
     "change_24h": -1.38,
     "change_7d": 5.23,
     "market_cap": 19530187.86,
     "volume_24h": 8414623.42351892
    },
    {
     "rank": 20,
     "id": 34330,
     "symbol": "FAI",
     "name": "Freysa",
     "slug": "freysa-ai",
     "price": 0.0022974885792732542,
     "change_1h": -0.23,
     "change_24h": -11.08,
     "change_7d": 15.34,
     "market_cap": 18815742.22,
     "volume_24h": 899846.35729596
    }
   ]
  }
 }
}