{
  "as_of_utc": "2026-07-15T05:48:11+00:00",
  "as_of_local": "2026-07-15 05:48:11 UTC",
  "delay_note": "Quotes delayed ~15 min \u2014 free Yahoo Finance data, no API key.",
  "errors": [],
  "stocks": [
    {
      "symbol": "NVDA",
      "name": "NVIDIA",
      "price": 203.53,
      "previous_close": 210.96,
      "change_pct": -3.52,
      "market_cap": 5130007800000.0,
      "headlines": [
        {
          "title": "New York enacts statewide moratorium on AI data center construction: A closer look",
          "url": "https://finance.yahoo.com/video/new-york-enacts-statewide-moratorium-on-ai-data-center-construction-a-closer-look-210912459.html",
          "publisher": "Yahoo Finance Video",
          "published": "2026-07-14T21:09:12Z"
        },
        {
          "title": "Cathie Wood of Ark Invest Thinks Bitcoin Has Finally Bottomed Out. If History Is Any Guide, This Is What Happens Next.",
          "url": "https://finance.yahoo.com/markets/crypto/articles/cathie-wood-ark-invest-thinks-053500624.html",
          "publisher": "Motley Fool",
          "published": "2026-07-15T05:35:00Z"
        },
        {
          "title": "2 Beaten-Down GLP-1 Stocks to Buy on the Dip",
          "url": "https://finance.yahoo.com/healthcare/articles/2-beaten-down-glp-1-052000613.html",
          "publisher": "Motley Fool",
          "published": "2026-07-15T05:20:00Z"
        }
      ]
    },
    {
      "symbol": "TSM",
      "name": "Taiwan Semiconductor (TSMC)",
      "price": 421.58,
      "previous_close": 434.11,
      "change_pct": -2.89,
      "market_cap": 2180341810325.0698,
      "headlines": [
        {
          "title": "3 Portfolio-Worthy Stocks to Consider as Q2 Earnings Approach: GE, TSM, UNH",
          "url": "https://finance.yahoo.com/markets/stocks/articles/3-portfolio-worthy-stocks-consider-234400527.html",
          "publisher": "Zacks",
          "published": "2026-07-14T23:44:00Z"
        },
        {
          "title": "Earnings, Warsh Testimony: What to Watch the Rest of the Week",
          "url": "https://www.wsj.com/finance/live/stock-market-today-dow-sp-500-nasdaq-07-15-2026-2a3dd235/card/earnings-warsh-testimony-what-to-watch-the-rest-of-the-week-dcb9fdde?siteid=yhoof2&yptr=yahoo",
          "publisher": "The Wall Street Journal",
          "published": "2026-07-14T23:22:15Z"
        },
        {
          "title": "Taiwan Semiconductor Manufacturing Company Limited (TSM) Not at Risk of Losing Competitive Edge, CEO Says",
          "url": "https://finance.yahoo.com/markets/stocks/articles/taiwan-semiconductor-manufacturing-company-limited-214512031.html",
          "publisher": "Insider Monkey",
          "published": "2026-07-14T21:45:12Z"
        }
      ]
    },
    {
      "symbol": "AVGO",
      "name": "Broadcom",
      "price": 384.05,
      "previous_close": 399.97,
      "change_pct": -3.98,
      "market_cap": 1851222030843.78,
      "headlines": [
        {
          "title": "Why Broadcom Stock Ticked Higher on Tuesday",
          "url": "https://finance.yahoo.com/markets/stocks/articles/why-broadcom-stock-ticked-higher-232800009.html",
          "publisher": "Motley Fool",
          "published": "2026-07-14T23:28:00Z"
        },
        {
          "title": "Broadcom Inc. (AVGO) Agreement a Strategic Positive for Apple, says Evercore ISI",
          "url": "https://finance.yahoo.com/technology/articles/broadcom-inc-avgo-agreement-strategic-214435793.html",
          "publisher": "Insider Monkey",
          "published": "2026-07-14T21:44:35Z"
        },
        {
          "title": "The Real Risk Inside Broadcom Stock",
          "url": "https://finance.yahoo.com/markets/stocks/articles/real-risk-inside-broadcom-stock-212246307.html",
          "publisher": "Trefis",
          "published": "2026-07-14T21:22:46Z"
        }
      ]
    },
    {
      "symbol": "MU",
      "name": "Micron Technology",
      "price": 937.0,
      "previous_close": 979.3,
      "change_pct": -4.32,
      "market_cap": 1110328994611.12,
      "headlines": [
        {
          "title": "GraniteShares launches new SK Hynix ETFs",
          "url": "https://finance.yahoo.com/video/graniteshares-launches-new-sk-hynix-etfs-203436945.html",
          "publisher": "Yahoo Finance Video",
          "published": "2026-07-14T20:34:36Z"
        },
        {
          "title": "Micron and Nvidia are powering a $700 billion chip profit boom: Chart of the Day",
          "url": "https://finance.yahoo.com/markets/article/micron-and-nvidia-are-powering-a-700-billion-chip-profit-boom-chart-of-the-day-100000068.html",
          "publisher": "Yahoo Finance",
          "published": "2026-07-14T10:00:00Z"
        },
        {
          "title": "SK Hynix, Samsung Shares Soar Amid Chip Rebound; Samsung Denies US Listing Plans",
          "url": "https://finance.yahoo.com/markets/stocks/articles/sk-hynix-samsung-shares-soar-045538000.html",
          "publisher": "Stocktwits",
          "published": "2026-07-15T04:55:38Z"
        }
      ]
    },
    {
      "symbol": "AMD",
      "name": "AMD",
      "price": 534.39,
      "previous_close": 557.89,
      "change_pct": -4.21,
      "market_cap": 893781128255.07,
      "headlines": [
        {
          "title": "Why FormFactor (FORM) Stock Is Trading Up Today",
          "url": "https://finance.yahoo.com/markets/stocks/articles/why-formfactor-form-stock-trading-215911328.html",
          "publisher": "StockStory",
          "published": "2026-07-14T21:59:11Z"
        },
        {
          "title": "Advanced Micro Devices, Inc. (AMD) Stock Surges as Goldman Sees Big Earnings Coming",
          "url": "https://finance.yahoo.com/markets/stocks/articles/advanced-micro-devices-inc-amd-214529133.html",
          "publisher": "Insider Monkey",
          "published": "2026-07-14T21:45:29Z"
        },
        {
          "title": "The Real Risk Inside Broadcom Stock",
          "url": "https://finance.yahoo.com/markets/stocks/articles/real-risk-inside-broadcom-stock-212246307.html",
          "publisher": "Trefis",
          "published": "2026-07-14T21:22:46Z"
        }
      ]
    },
    {
      "symbol": "INTC",
      "name": "Intel",
      "price": 103.12,
      "previous_close": 109.84,
      "change_pct": -6.12,
      "market_cap": 541601760000.0,
      "headlines": [
        {
          "title": "Intel turns to next-generation ASML tool to help make its laptop chips",
          "url": "https://finance.yahoo.com/technology/articles/intel-turns-next-generation-asml-051144402.html",
          "publisher": "Reuters",
          "published": "2026-07-15T05:11:44Z"
        },
        {
          "title": "SK Hynix, Samsung Shares Soar Amid Chip Rebound; Samsung Denies US Listing Plans",
          "url": "https://finance.yahoo.com/markets/stocks/articles/sk-hynix-samsung-shares-soar-045538000.html",
          "publisher": "Stocktwits",
          "published": "2026-07-15T04:55:38Z"
        },
        {
          "title": "Cadence Design Systems vs. Synopsys: Which Technology Stock Is a Better Buy in 2026?",
          "url": "https://finance.yahoo.com/markets/stocks/articles/cadence-design-systems-vs-synopsys-233903680.html",
          "publisher": "Motley Fool",
          "published": "2026-07-14T23:39:03Z"
        }
      ]
    },
    {
      "symbol": "ARM",
      "name": "Arm Holdings",
      "price": 281.17,
      "previous_close": 298.99,
      "change_pct": -5.96,
      "market_cap": 299180027138.4021,
      "headlines": [
        {
          "title": "This Analyst Just Downgraded ARM Stock. Here's Why.",
          "url": "https://finance.yahoo.com/markets/stocks/articles/analyst-just-downgraded-arm-stock-203513785.html",
          "publisher": "Barchart",
          "published": "2026-07-14T20:35:13Z"
        },
        {
          "title": "Arm Holdings plc (ARM) CEO says US would have Difficulty Banning AI CPU chip Exports to China",
          "url": "https://finance.yahoo.com/technology/ai/articles/arm-holdings-plc-arm-ceo-185557648.html",
          "publisher": "Insider Monkey",
          "published": "2026-07-14T18:55:57Z"
        },
        {
          "title": "Intel, ARM face near-term pain while AMD rides server boom: BofA",
          "url": "https://finance.yahoo.com/markets/stocks/articles/intel-arm-face-near-term-173700806.html",
          "publisher": "Proactive",
          "published": "2026-07-14T17:37:00Z"
        }
      ]
    },
    {
      "symbol": "MRVL",
      "name": "Marvell Technology",
      "price": 217.53,
      "previous_close": 235.81,
      "change_pct": -7.75,
      "market_cap": 199649781452.12,
      "headlines": [
        {
          "title": "The Real Risk Inside Broadcom Stock",
          "url": "https://finance.yahoo.com/markets/stocks/articles/real-risk-inside-broadcom-stock-212246307.html",
          "publisher": "Trefis",
          "published": "2026-07-14T21:22:46Z"
        },
        {
          "title": "NVIDIA Stock Amplifies Your Market Ride",
          "url": "https://finance.yahoo.com/markets/stocks/articles/nvidia-stock-amplifies-market-ride-211111927.html",
          "publisher": "Trefis",
          "published": "2026-07-14T21:11:11Z"
        },
        {
          "title": "TYLSemi raises $43 million to create building blocks of custom AI chips",
          "url": "https://finance.yahoo.com/technology/ai/articles/tylsemi-raises-43-million-create-185440426.html",
          "publisher": "Reuters",
          "published": "2026-07-14T18:54:40Z"
        }
      ]
    },
    {
      "symbol": "QCOM",
      "name": "Qualcomm",
      "price": 183.98,
      "previous_close": 189.16,
      "change_pct": -2.74,
      "market_cap": 187717400000.0,
      "headlines": [
        {
          "title": "Qualcomm (QCOM) Stock Falls Amid Market Uptick: What Investors Need to Know",
          "url": "https://finance.yahoo.com/markets/stocks/articles/qualcomm-qcom-stock-falls-amid-214503144.html",
          "publisher": "Zacks",
          "published": "2026-07-14T21:45:03Z"
        },
        {
          "title": "The Real Risk Inside Broadcom Stock",
          "url": "https://finance.yahoo.com/markets/stocks/articles/real-risk-inside-broadcom-stock-212246307.html",
          "publisher": "Trefis",
          "published": "2026-07-14T21:22:46Z"
        },
        {
          "title": "NVIDIA Stock Amplifies Your Market Ride",
          "url": "https://finance.yahoo.com/markets/stocks/articles/nvidia-stock-amplifies-market-ride-211111927.html",
          "publisher": "Trefis",
          "published": "2026-07-14T21:11:11Z"
        }
      ]
    },
    {
      "symbol": "NXPI",
      "name": "NXP Semiconductors",
      "price": 278.39,
      "previous_close": 292.26,
      "change_pct": -4.75,
      "market_cap": 71668965195.73,
      "headlines": [
        {
          "title": "NXP Semiconductors (NXPI) Stock Looks Fair On Cash Flow Yet Cheap On Earnings",
          "url": "https://finance.yahoo.com/markets/stocks/articles/nxp-semiconductors-nxpi-stock-looks-051127209.html",
          "publisher": "Simply Wall St.",
          "published": "2026-07-15T05:11:27Z"
        },
        {
          "title": "NXP Semiconductors (NXPI) Outpaces Stock Market Gains: What You Should Know",
          "url": "https://finance.yahoo.com/markets/stocks/articles/nxp-semiconductors-nxpi-outpaces-stock-221503605.html",
          "publisher": "Zacks",
          "published": "2026-07-14T22:15:03Z"
        },
        {
          "title": "Price Prediction: ON Semiconductor\u2019s Rally May Be Far From Over",
          "url": "https://finance.yahoo.com/markets/stocks/articles/price-prediction-semiconductor-rally-may-120050125.html",
          "publisher": "24/7 Wall St.",
          "published": "2026-07-14T12:00:50Z"
        }
      ]
    },
    {
      "symbol": "LSCC",
      "name": "Lattice Semiconductor",
      "price": 130.74,
      "previous_close": 137.44,
      "change_pct": -4.87,
      "market_cap": 18346722130.87,
      "headlines": [
        {
          "title": "MACOM, Lattice Semiconductor, and Amtech Shares Skyrocket, What You Need To Know",
          "url": "https://finance.yahoo.com/markets/stocks/articles/macom-lattice-semiconductor-amtech-shares-213511796.html",
          "publisher": "StockStory",
          "published": "2026-07-14T21:35:11Z"
        },
        {
          "title": "Lattice Semiconductor CEO Ford Tamer Sells Shares. What Does This Mean for Investors?",
          "url": "https://finance.yahoo.com/markets/stocks/articles/lattice-semiconductor-ceo-ford-tamer-191602555.html",
          "publisher": "Motley Fool",
          "published": "2026-07-14T19:16:02Z"
        },
        {
          "title": "Lattice Semiconductor (LSCC) Stock Trades Up, Here Is Why",
          "url": "https://finance.yahoo.com/markets/stocks/articles/lattice-semiconductor-lscc-stock-trades-225201400.html",
          "publisher": "StockStory",
          "published": "2026-07-06T22:52:01Z"
        }
      ]
    },
    {
      "symbol": "AVAV",
      "name": "AeroVironment",
      "price": 141.8,
      "previous_close": 144.58,
      "change_pct": -1.92,
      "market_cap": 7260734064.1,
      "headlines": [
        {
          "title": "Drone Stocks Are Back In Play: Why RCAT, AVAV, KTOS, UMAC Stocks Are Climbing",
          "url": "https://finance.yahoo.com/markets/stocks/articles/drone-stocks-back-play-why-051944484.html",
          "publisher": "Stocktwits",
          "published": "2026-07-14T05:19:44Z"
        },
        {
          "title": "AeroVironment Flies Under Wall Street\u2019s Radar Toward a $4 Billion Target",
          "url": "https://finance.yahoo.com/markets/stocks/articles/aerovironment-flies-under-wall-street-154500859.html",
          "publisher": "MarketBeat",
          "published": "2026-07-10T15:45:00Z"
        },
        {
          "title": "AeroVironment Plots Revenue Doubling to $4 Billion on Defense Drone Demand",
          "url": "https://finance.yahoo.com/technology/articles/aerovironment-plots-revenue-doubling-4-020205014.html",
          "publisher": "MarketBeat",
          "published": "2026-07-10T02:02:05Z"
        }
      ]
    },
    {
      "symbol": "SYNA",
      "name": "Synaptics",
      "price": 119.15,
      "previous_close": 126.76,
      "change_pct": -6.0,
      "market_cap": 4798459119.84,
      "headlines": [
        {
          "title": "ON Jumps 67% Year to Date: Buy, Sell or Hold the Stock?",
          "url": "https://finance.yahoo.com/markets/stocks/articles/jumps-67-date-buy-sell-155400695.html",
          "publisher": "Zacks",
          "published": "2026-07-14T15:54:00Z"
        },
        {
          "title": "The 5 Smartphone Chip Stocks Poised for the Next Handset Upgrade Wave",
          "url": "https://finance.yahoo.com/technology/articles/5-smartphone-chip-stocks-poised-123035239.html",
          "publisher": "24/7 Wall St.",
          "published": "2026-07-11T12:30:35Z"
        },
        {
          "title": "Onsemi\u2019s Synaptics acquisition could unlock long-term synergies, says Bank of America",
          "url": "https://finance.yahoo.com/technology/articles/onsemi-synaptics-acquisition-could-unlock-200200733.html",
          "publisher": "Proactive",
          "published": "2026-07-09T20:02:00Z"
        }
      ]
    },
    {
      "symbol": "CEVA",
      "name": "CEVA",
      "price": 42.71,
      "previous_close": 45.54,
      "change_pct": -6.21,
      "market_cap": 1212718332.57,
      "headlines": [
        {
          "title": "Why CEVA (CEVA) Is Up 12.7% After Securing Landmark Edge AI Licensing Deal With Platform Giant",
          "url": "https://finance.yahoo.com/technology/ai/articles/why-ceva-ceva-12-7-160735099.html",
          "publisher": "Simply Wall St.",
          "published": "2026-07-11T16:07:35Z"
        },
        {
          "title": "CEVA (CEVA) Lands A New AI Deal, Does It Look Fully Valued?",
          "url": "https://finance.yahoo.com/markets/stocks/articles/ceva-ceva-lands-ai-deal-131105879.html",
          "publisher": "Simply Wall St.",
          "published": "2026-07-11T13:11:05Z"
        },
        {
          "title": "Analysts Think AI Demand Has No Ceiling And Raised AMD\u2019s Price Target Again",
          "url": "https://finance.yahoo.com/technology/ai/articles/analysts-think-ai-demand-no-160100629.html",
          "publisher": "24/7 Wall St.",
          "published": "2026-07-10T16:01:00Z"
        }
      ]
    }
  ],
  "etfs": [
    {
      "symbol": "DRAM",
      "name": "Roundhill Memory ETF",
      "price": 61.23,
      "change_pct": 6.86,
      "holdings": [
        {
          "symbol": "MU",
          "name": "Micron Technology Inc",
          "short": "Micron",
          "weight_pct": 27.63,
          "change_pct": -4.32,
          "price": 937.0,
          "currency": "USD"
        },
        {
          "symbol": "000660.KS",
          "name": "SK hynix",
          "short": "SK hynix",
          "weight_pct": 27.17,
          "change_pct": 9.1,
          "price": 2087000.0,
          "currency": "KRW"
        },
        {
          "symbol": "005930.KS",
          "name": "Samsung Electronics Co",
          "short": "Samsung",
          "weight_pct": 19.2,
          "change_pct": 5.51,
          "price": 277500.0,
          "currency": "KRW"
        },
        {
          "symbol": "285A.T",
          "name": "Kioxia Holdings",
          "short": "Kioxia",
          "weight_pct": 7.7,
          "change_pct": 5.17,
          "price": 72670.0,
          "currency": "JPY"
        },
        {
          "symbol": "SNDK",
          "name": "Sandisk",
          "short": "Sandisk",
          "weight_pct": 5.05,
          "change_pct": 5.01,
          "price": 1757.82,
          "currency": "USD"
        },
        {
          "symbol": "STX",
          "name": "Seagate Technology Holdings",
          "short": "Seagate",
          "weight_pct": 4.09,
          "change_pct": -5.46,
          "price": 860.66,
          "currency": "USD"
        },
        {
          "symbol": "WDC",
          "name": "Western Digital",
          "short": "Western",
          "weight_pct": 3.67,
          "change_pct": -4.64,
          "price": 555.55,
          "currency": "USD"
        },
        {
          "symbol": "2408.TW",
          "name": "Nanya Technology",
          "short": "Nanya",
          "weight_pct": 3.13,
          "change_pct": 7.25,
          "price": 480.5,
          "currency": "TWD"
        },
        {
          "symbol": "2344.TW",
          "name": "Winbond Electronics",
          "short": "Winbond",
          "weight_pct": 1.82,
          "change_pct": 9.73,
          "price": 180.5,
          "currency": "TWD"
        }
      ]
    }
  ],
  "etf": {
    "symbol": "DRAM",
    "name": "Roundhill Memory ETF",
    "price": 61.23,
    "change_pct": 6.86,
    "holdings": [
      {
        "symbol": "MU",
        "name": "Micron Technology Inc",
        "short": "Micron",
        "weight_pct": 27.63,
        "change_pct": -4.32,
        "price": 937.0,
        "currency": "USD"
      },
      {
        "symbol": "000660.KS",
        "name": "SK hynix",
        "short": "SK hynix",
        "weight_pct": 27.17,
        "change_pct": 9.1,
        "price": 2087000.0,
        "currency": "KRW"
      },
      {
        "symbol": "005930.KS",
        "name": "Samsung Electronics Co",
        "short": "Samsung",
        "weight_pct": 19.2,
        "change_pct": 5.51,
        "price": 277500.0,
        "currency": "KRW"
      },
      {
        "symbol": "285A.T",
        "name": "Kioxia Holdings",
        "short": "Kioxia",
        "weight_pct": 7.7,
        "change_pct": 5.17,
        "price": 72670.0,
        "currency": "JPY"
      },
      {
        "symbol": "SNDK",
        "name": "Sandisk",
        "short": "Sandisk",
        "weight_pct": 5.05,
        "change_pct": 5.01,
        "price": 1757.82,
        "currency": "USD"
      },
      {
        "symbol": "STX",
        "name": "Seagate Technology Holdings",
        "short": "Seagate",
        "weight_pct": 4.09,
        "change_pct": -5.46,
        "price": 860.66,
        "currency": "USD"
      },
      {
        "symbol": "WDC",
        "name": "Western Digital",
        "short": "Western",
        "weight_pct": 3.67,
        "change_pct": -4.64,
        "price": 555.55,
        "currency": "USD"
      },
      {
        "symbol": "2408.TW",
        "name": "Nanya Technology",
        "short": "Nanya",
        "weight_pct": 3.13,
        "change_pct": 7.25,
        "price": 480.5,
        "currency": "TWD"
      },
      {
        "symbol": "2344.TW",
        "name": "Winbond Electronics",
        "short": "Winbond",
        "weight_pct": 1.82,
        "change_pct": 9.73,
        "price": 180.5,
        "currency": "TWD"
      }
    ]
  },
  "tape": [
    {
      "label": "SPX",
      "price": 7515.34,
      "change_pct": -0.79
    },
    {
      "label": "BTC",
      "price": 64693.5,
      "change_pct": 3.94
    },
    {
      "label": "Gold",
      "price": 4034.9,
      "change_pct": -0.65
    },
    {
      "label": "Nasdaq100",
      "price": 29264.1,
      "change_pct": -1.88
    }
  ]
}