{
 "meta": {
  "section": "hot_tickers",
  "as_of": "2026-07-14T20:06:58+00:00",
  "refresh_cycle": "15m quantitative; editorial enrichment each 4h takeaways cycle",
  "heat_criteria": "Any 2 of: |day move| > 5%; volume > 3x 30d avg; news catalyst within 4h. Rank by heat_score. Losers qualify \u2014 hot means attention, not direction. Never padded.",
  "disclaimer": "For informational purposes only. Not investment advice."
 },
 "hot_tickers": [
  {
   "rank": 1,
   "ticker": "IBM",
   "company": "International Business Machines Corp",
   "move_pct": -25.06,
   "price": 217.51,
   "volume": 64006891,
   "volume_vs_avg": "~6x",
   "heat_score": 99,
   "direction": "down",
   "why": "IBM Warning Hits Software Stocks",
   "catalyst_type": "momentum_narrative",
   "source_url": "https://finance.yahoo.com/markets/stocks/articles/ibm-warning-hits-software-stocks-192217475.html",
   "published": "2026-07-14T19:22:17Z",
   "sector": "Applied AI: Industrial, Defense & Vertical"
  },
  {
   "rank": 2,
   "ticker": "CRWD",
   "company": "Crowdstrike Holdings Inc",
   "move_pct": 12.31,
   "price": 211.03,
   "volume": 11636383,
   "volume_vs_avg": "~0.9x",
   "heat_score": 72,
   "direction": "up",
   "why": "Stock Market Today: Nasdaq Shows Strength; CrowdStrike Sprints Higher (Live Coverage)",
   "catalyst_type": "momentum_narrative",
   "source_url": "https://www.investors.com/market-trend/stock-market-today/dow-jones-sp500-nasdaq-june-cpi-inflation-ibm-stock/?src=A00220&yptr=yahoo",
   "published": "2026-07-14T19:18:01Z",
   "sector": "AI Software & Cloud Infrastructure"
  },
  {
   "rank": 3,
   "ticker": "ISRG",
   "company": "Intuitive Surgical Inc",
   "move_pct": -6.69,
   "price": 379.88,
   "volume": 5668144,
   "volume_vs_avg": "~2x",
   "heat_score": 49,
   "direction": "down",
   "why": "Why This Group Of Medical Giants, Including Intuitive Surgical, Just Took A Tumble",
   "catalyst_type": "momentum_narrative",
   "source_url": "https://www.investors.com/news/technology/intuitive-surgical-stock-surgeries-decline-hca-healthcare/?src=A00220&yptr=yahoo",
   "published": "2026-07-14T19:40:57Z",
   "sector": "Applied AI: Industrial, Defense & Vertical"
  },
  {
   "rank": 4,
   "ticker": "DELL",
   "company": "Dell Technologies Inc",
   "move_pct": 7.0,
   "price": 457.0,
   "volume": 6335668,
   "volume_vs_avg": "~0.6x",
   "heat_score": 43,
   "direction": "up",
   "why": "Dell and Hewlett Packard Enterprise Shares Skyrocket, What You Need To Know",
   "catalyst_type": "momentum_narrative",
   "source_url": "https://finance.yahoo.com/markets/stocks/articles/dell-hewlett-packard-enterprise-shares-193511620.html",
   "published": "2026-07-14T19:35:11Z",
   "sector": "Chip Equipment & AI Hardware"
  },
  {
   "rank": 5,
   "ticker": "PANW",
   "company": "Palo Alto Networks Inc",
   "move_pct": 6.87,
   "price": 353.0,
   "volume": 5863860,
   "volume_vs_avg": "~0.7x",
   "heat_score": 42,
   "direction": "up",
   "why": "CrowdStrike Climbs 11%, Palo Alto Rises 7% as Cybersecurity Stocks Rally on Cooling Inflation",
   "catalyst_type": "momentum_narrative",
   "source_url": "https://finance.yahoo.com/markets/stocks/articles/crowdstrike-climbs-11-palo-alto-171612684.html",
   "published": "2026-07-14T17:16:12Z",
   "sector": "AI Software & Cloud Infrastructure"
  },
  {
   "rank": 6,
   "ticker": "ZS",
   "company": "Zscaler Inc",
   "move_pct": 6.61,
   "price": 151.19,
   "volume": 3554414,
   "volume_vs_avg": "~0.8x",
   "heat_score": 42,
   "direction": "up",
   "why": "Why Are Zscaler (ZS) Shares Soaring Today",
   "catalyst_type": "momentum_narrative",
   "source_url": "https://finance.yahoo.com/markets/stocks/articles/why-zscaler-zs-shares-soaring-191911505.html",
   "published": "2026-07-14T19:19:11Z",
   "sector": "AI Software & Cloud Infrastructure"
  },
  {
   "rank": 7,
   "ticker": "ARM",
   "company": "Arm Holdings Plc ADR",
   "move_pct": -6.02,
   "price": 281.0,
   "volume": 8314663,
   "volume_vs_avg": "~0.8x",
   "heat_score": 40,
   "direction": "down",
   "why": "Arm Holdings plc (ARM) CEO says US would have Difficulty Banning AI CPU chip Exports to China",
   "catalyst_type": "regulatory",
   "source_url": "https://finance.yahoo.com/technology/ai/articles/arm-holdings-plc-arm-ceo-185557648.html",
   "published": "2026-07-14T18:55:57Z",
   "sector": "AI Chips & Compute"
  }
 ]
}