{
 "session": "Overnight",
 "generated_et": "Tue Jul 7, 2026 \u00b7 8:24 PM ET",
 "generated_utc": "2026-07-08T00:24:23+00:00",
 "since_last": "31% of 84 AI names green; AI Applications & Data Software leads +0.36%; AI bubble risk 57 Heating Up.",
 "cards": [
  {
   "headline": "The tape: broad selling, 31% of AI names green",
   "body": "SPX -0.45% \u00b7 BTC -0.98% \u00b7 Gold -1.12% \u00b7 Nasdaq100 -1.77%. 31% of 84 AI names are green \u2014 broad selling. AI Applications & Data Software is doing the heavy lifting at +0.36%.",
   "tickers": [],
   "watch": null
  },
  {
   "headline": "AI Applications & Data Software leads, Chip Equipment & AI Hardware lags",
   "body": "Strongest AI sector is AI Applications & Data Software at +0.36%; weakest is Chip Equipment & AI Hardware at -4.47%. Rotation within the AI trade, not a one-way move.",
   "tickers": [],
   "watch": null
  },
  {
   "headline": "AMBA is the standout at -9.92%",
   "body": "Leaders: NET +8.60%, WDAY +4.10%, INTU +3.32%, NOW +2.59%, META +2.55%. Laggards: AMBA -9.92%, INTC -9.66%, TER -9.59%, AVAV -8.09%.",
   "tickers": [
    "NET",
    "WDAY",
    "INTU",
    "NOW",
    "META",
    "AMBA"
   ],
   "watch": "Hot means attention, not direction \u2014 watch whether the leaders hold the bid or fade into the next session."
  },
  {
   "headline": "SpaceX (SPCX) -6.83% at $149.47",
   "body": "The SpaceX debut keeps pulling attention \u2014 SPCX is -6.83% this session. The biggest IPO in history remains the tape's attention magnet.",
   "tickers": [
    "SPCX"
   ],
   "watch": null
  },
  {
   "headline": "Risk: AI bubble index 57 \u2014 Heating Up",
   "body": "The composite AI Bubble Index sits at 57/100, led by Valuation at 85. Higher = frothier; the risk is everyone caring at once while valuations are already stretched.",
   "tickers": [],
   "watch": null
  }
 ]
}